Workbook

Sheet Total
B1: PJR-GC-Migrate Orchestra
B3: Digital Rev (BD Phase) | C3: =Digital_Manday!O25 -> 146000
B4: Digital Rev (Development Phase) | C4: =Digital_Manday!O26 -> 1929500 | D4: =SUM(C3:C4) -> 2075500
B6: Vendor Cost + 10 % | C6: =('Vendor Cost'!E15)*110% -> 137500
B8: Total | C8: =SUM(C3:C6)+C7 -> 2213000
B11: ค่าเดินทาง | C11: จำนวนครั้ง | D11: ครั้งละ | E11: รวมค่าเดินทาง
E12: =C12*D12 -> 0
E13: =C13*D13 -> 0
E14: =C14*D14 -> 0
D15: Total | E15: =SUM(E12:E14) -> 0
B17: ค่าเบี้ยเลี้ยง | C17: จำนวนครั้ง | D17: ครั้งละ | E17: รวมค่าเบี้ยเลี้ยง
E18: =C18*D18 -> 0
E19: =C19*D19 -> 0
E20: =C20*D20 -> 0
D21: Total | E21: =SUM(E18:E20) -> 0
B24: งวดการชำระเงิน PTTOR >> PTT Digital | C24: % | D24: จำนวนเงิน
B25: งวดที่ 1 : Sign-Off M1 | C25: 0.6 | D25: =($C$8-$C$7)*C25 -> 1327800 | G25: Cost Performance
B26: งวดที่ 2 : Sign-Off M2 | C26: 0.4 | D26: =($C$8-$C$7)*C26 -> 885200
C30: =SUM(C25:C29) -> 1 | D30: =SUM(D25:D29) -> 2213000
B32: งวดการชำระเงิน PTT Digital >> Vendor | C32: % | D32: จำนวนเงิน

Sheet Vendor Cost
C2: =Total!B1 -> PJR-GC-Migrate Orchestra
C3: Vendor :
C5: Order | D5: Description | E5: Cost
C6: 1 | D6: SIMPLICITY ODM | E6: 125000
C7: 2
C8: 3
C9: 4
C10: 5
C11: 6
C12: 7
D13: Total | E13: =SUM(E6:E12) -> 125000
D14: Discount
D15: Grand Total | E15: =E13-E14 -> 125000
D16: ราคานี้ยังไม่รวม Vat 7%
C18: Order | D18: Description | E18: Cost
D24: Total | E24: =SUM(E20:E23) -> 0

Sheet Digital_Manday
A1: =Total!B1 -> PJR-GC-Migrate Orchestra
A2: =CONCATENATE("(ระยะเวลาโครงการ ",Total!C1," วัน)") -> (ระยะเวลาโครงการ วัน) | D2: Sr1 | E2: Sr1 | F2: Sr1 | G2: Sr2 | H2: Of2 | I2: Of2 | J2: Of1 | K2: Sr1 | L2: Sr2 | M2: Of2 | N2: Of2
A3: Phase | B3: Details | C3: Deliverables | D3: PM | E3: Legacy Team | F3: Legacy Team | G3: MuleSoft | H3: Legacy Team | I3: Legacy Team | J3: MuleSoft | K3: MuleSoft | L3: QA | M3: Network | N3: Infra
D4: Panita Y. | E4: Benjo C. | F4: Thanakorn B. | G4: Tawit C. | H4: Thongchai T. | I4: Weerapol K. | J4: Warisara B. | K4: Pantawat K. | L4: Sinvisa N. | M4: Panuwat K. | N4: Pawinee K.
A5: Business Development | B5: Gather Initial Requirements | C5: Proposal | D5: 5 | E5: 1 | F5: 1 | G5: 1 | H5: 1 | I5: 1 | J5: 1 | K5: 1
B6: Vendor Selection
B7: Impact analyst
A8: Project Planning | B8: Kick-Off Meeting | C8: Kick Off Presentation, Project Schedule | D8: 4 | E8: 1 | F8: 1 | G8: 1 | H8: 1 | I8: 1 | J8: 1
B9: Create Project Plan, Other Plans and Integrate to Project Plan | K9: 1
B10: Prepare and setup Development Environment
A11: Design | B11: Send URL Mulesoft | D11: 4 | E11: 2 | F11: 2 | G11: 2 | H11: 2 | I11: 2 | J11: 6 | K11: 6 | N11: 1
B12: Confirm with Legacy
A13: Software Development | B13: Develop Software | C13: Sign-Off M1 | D13: 4 | E13: 26 | F13: 22 | G13: 2 | H13: 16 | I13: 16 | J13: 10 | K13: 10 | L13: 3 | M13: 3 | N13: 3
B14: Unit Test
B15: QA
A16: Final Preparation | B16: Prepare Transport | D16: 3 | E16: 2 | F16: 2 | G16: 2 | H16: 2 | I16: 2 | J16: 2
B17: Prepare Firewall | K17: 2
B18: Technical
A19: Project Closure | B19: Go-live Support and Go-live Sign off | C19: Sign-Off GO Live | D19: 2
B20: Create Project closure report and Completion sign-off
A21: Total | D21: =SUM(D5:D20) -> 22 | E21: =SUM(E5:E20) -> 32 | F21: =SUM(F5:F20) -> 28 | G21: =SUM(G5:G20) -> 8 | H21: =SUM(H5:H20) -> 22 | I21: =SUM(I5:I20) -> 22 | J21: =SUM(J5:J20) -> 20 | K21: =SUM(K5:K20) -> 20 | ... N21: =SUM(N5:N20) -> 4
O23: Digital Rev
C24: Rev/ Day | D24: 14000 | E24: 14000 | F24: 14000 | G24: 14000 | H24: 8500 | I24: 8500 | J24: 8500 | K24: 8500 | L24: 14000 | M24: 8500 | N24: 8500
C25: Rev (BD Phase) | D25: =D5*D24 -> 70000 | E25: =E5*E24 -> 14000 | F25: =F5*F24 -> 14000 | G25: =G5*G24 -> 14000 | H25: =H5*H24 -> 8500 | I25: =I5*I24 -> 8500 | J25: =J5*J24 -> 8500 | K25: =K5*K24 -> 8500 | ... N25: =N5*N24 -> 0 | O25: =SUM(D25:N25) -> 146000
C26: Rev (Development Phase) | D26: =(D21-D5)*D24 -> 238000 | E26: =(E21-E5)*E24 -> 434000 | F26: =(F21-F5)*F24 -> 378000 | G26: =(G21-G5)*G24 -> 98000 | H26: =(H21-H5)*H24 -> 178500 | I26: =(I21-I5)*I24 -> 178500 | J26: =(J21-J5)*J24 -> 161500 | K26: =(K21-K5)*K24 -> 161500 | ... N26: =(N21-N5)*N24 -> 34000 | O26: =SUM(D26:N26) -> 1929500
O27: =SUM(O25:O26) -> 2075500
O28: Digital Cost
C29: Cost/ Day | D29: =IF(D2="Sr1",6200,IF(D2="Sr2",9200,IF(D2="Of1",3500,IF(D2="Of2",4900)))) -> 6200 | E29: =IF(E2="Sr1",6200,IF(E2="Sr2",9200,IF(E2="Of1",3500,IF(E2="Of2",4900)))) -> 6200 | F29: =IF(F2="Sr1",6200,IF(F2="Sr2",9200,IF(F2="Of1",3500,IF(F2="Of2",4900)))) -> 6200 | G29: =IF(G2="Sr1",6200,IF(G2="Sr2",9200,IF(G2="Of1",3500,IF(G2="Of2",4900)))) -> 9200 | H29: =IF(H2="Sr1",6200,IF(H2="Sr2",9200,IF(H2="Of1",3500,IF(H2="Of2",4900)))) -> 4900 | I29: =IF(I2="Sr1",6200,IF(I2="Sr2",9200,IF(I2="Of1",3500,IF(I2="Of2",4900)))) -> 4900 | J29: =IF(J2="Sr1",6200,IF(J2="Sr2",9200,IF(J2="Of1",3500,IF(J2="Of2",4900)))) -> 3500 | K29: =IF(K2="Sr1",6200,IF(K2="Sr2",9200,IF(K2="Of1",3500,IF(K2="Of2",4900)))) -> 6200 | ... N29: =IF(N2="Sr1",6200,IF(N2="Sr2",9200,IF(N2="Of1",3500,IF(N2="Of2",4900)))) -> 4900
C30: Cost (Development Phase) | D30: =D29*D21 -> 136400 | E30: =E29*E21 -> 198400 | F30: =F29*F21 -> 173600 | G30: =G29*G21 -> 73600 | H30: =H29*H21 -> 107800 | I30: =I29*I21 -> 107800 | J30: =J29*J21 -> 70000 | K30: =K29*K21 -> 124000 | ... N30: =N29*N21 -> 19600 | O30: =SUM(D30:N30) -> 1053500
O31: =SUM(O30:O30) -> 1053500

Sheet Timeline
B2: Task/Timeline | C2: Month 1 | G2: Month 2 | K2: Month 3
C3: 1 | D3: 2 | E3: 3 | F3: 4 | G3: 1 | H3: 2 | I3: 3 | J3: 4 | K3: 1 | L3: 2 | M3: 3 | N3: 4
B4: Requirement Gathering
B5: Confirm Prototype
B6: Sign off Requirement and Design Specification
B7: Development
B8: SIT
B9: UAT
B10: Security Scan and Performance Test
B11: Implement Production
B12: Migrate Data
B13: Go-Live

Sheet Other Expense
B2: หัวข้อ | C2: ครั้งที่ 1 | F2: ครั้งที่ 2 | I2: ครั้งที่ 3 | L2: ครั้งที่ 4 | O2: ครั้งที่ 5 | R2: ครั้งที่ 6 | U2: ครั้งที่ 7 | X2: ครั้งที่ 8 | AA2: ครั้งที่ 9 | AD2: ครั้งที่ 10
C3: คน | D3: คัน | E3: ค้าง | F3: คน | G3: คัน | H3: ค้าง | I3: คน | J3: คัน | K3: ค้าง | L3: คน | M3: คัน | N3: ค้าง | O3: คน | P3: คัน | Q3: ค้าง | R3: คน | S3: คัน | T3: ค้าง | U3: คน | V3: คัน | W3: ค้าง | X3: คน | Y3: คัน | Z3: ค้าง | AA3: คน | AB3: คัน | AC3: ค้าง | AD3: คน | AE3: คัน | AF3: ค้าง
B4: BD
B5: Kick-Off
B6: Requirement Gathering
B7: Confirm Requirement and Design
B8: UAT
B9: Training
B10: Project Closure
B11: Sum | C11: =SUM(C4:C10) -> 0 | D11: =SUM(D4:D10) -> 0 | E11: =SUM(E4:E10) -> 0 | F11: =SUM(F4:F10) -> 0 | G11: =SUM(G4:G10) -> 0 | H11: =SUM(H4:H10) -> 0
C12: =C11*600+D11*2500+E11*2500 -> 0 | F12: =F11*600+G11*2500+H11*2500 -> 0
B15: ค่าเดินทาง | C15: =(D11+G11+J11+M11+P11+S11+V11+Y11+AB11+AE11) -> 0 | D15: =(D11+G11+J11+M11+P11+S11+V11+Y11+AB11+AE11)*2500 -> 0
B16: ค่าที่พัก | C16: =(E11+H11+K11+N11+Q11+T11+W11+Z11+AC11+AF11) -> 0 | D16: =C16*2500 -> 0
B17: ต่าเบี้ยเลี้ยง | C17: =(C11+F11+I11+L11+O11+R11+U11+X11+AA11+AD11) -> 0 | D17: =(C11+F11+I11+L11+O11+R11+U11+X11+AA11+AD11)*600 -> 0
D18: =SUM(D15:D17) -> 0
